survivors/__init__.py
survivors/constants.py
survivors/criteria.py
survivors/metrics.py
survivors/datasets/__init__.py
survivors/datasets/backblaze.py
survivors/datasets/covid.py
survivors/datasets/crm.py
survivors/datasets/new_backblaze.py
survivors/datasets/onk.py
survivors/datasets/other.py
survivors/datasets/reliability.py
survivors/datasets/data/Framingham.csv
survivors/datasets/data/GBSG.csv
survivors/datasets/data/__init__.py
survivors/datasets/data/actg.csv
survivors/datasets/data/covid_train.xlsx
survivors/datasets/data/flchain.csv
survivors/datasets/data/metabric.tsv
survivors/datasets/data/mimic.csv.gz
survivors/datasets/data/pbc.csv
survivors/datasets/data/rott2.csv
survivors/datasets/data/seer.csv
survivors/datasets/data/smarto.csv
survivors/datasets/data/support2.csv.gz
survivors/datasets/data/CRM/C2CVariableMeaning.xlsx
survivors/datasets/data/CRM/Churn_Modelling.csv
survivors/datasets/data/CRM/ECommerce.xlsx
survivors/datasets/data/CRM/__init__.py
survivors/datasets/data/CRM/cell2cell-duke univeristy.csv.gz
survivors/datasets/data/CRM/gym_churn_us.csv
survivors/datasets/data/CRM/telco.csv.gz
survivors/datasets/data/RELIABILITY/Cut_Alibaba.csv.gz
survivors/ensemble/__init__.py
survivors/ensemble/base_ensemble.py
survivors/ensemble/base_ensemble_iter.py
survivors/ensemble/boosting.py
survivors/ensemble/bootstrap.py
survivors/ensemble/bootstrap_iter.py
survivors/ensemble/clever_boosting.py
survivors/ensemble/clever_boosting_iter.py
survivors/ensemble/ibsboosting.py
survivors/ensemble/proboosting.py
survivors/experiments/__init__.py
survivors/experiments/grid.py
survivors/external/__init__.py
survivors/external/leaf_model.py
survivors/external/mlwrap.py
survivors/external/nonparametric.py
survivors/external/parametric.py
survivors/scheme/__init__.py
survivors/scheme/scheme.py
survivors/tree/__init__.py
survivors/tree/decision_tree.py
survivors/tree/find_split_hist.py
survivors/tree/node.py
survivors/visualize/__init__.py
survivors/visualize/base.py
survivors-1.8.0.dist-info/licenses/LICENSE
survivors-1.8.0.dist-info/METADATA
survivors-1.8.0.dist-info/WHEEL
survivors-1.8.0.dist-info/top_level.txt
survivors-1.8.0.dist-info/RECORD
