Metadata-Version: 2.4
Name: survivors
Version: 1.8.0
Author: Iulii Vasilev
Author-email: iuliivasilev@gmail.com
License: BSD 3-Clause License
Keywords: survival analysis,time-to-event,event data,machine learning
Requires-Python: >=3.10
License-File: LICENSE
Requires-Dist: joblib>=1.2.0
Requires-Dist: numpy>=1.22
Requires-Dist: numba>=0.58.0
Requires-Dist: matplotlib>=3.5.0
Requires-Dist: seaborn
Requires-Dist: graphviz>=0.20
Requires-Dist: pandas>=0.25
Requires-Dist: scikit-learn>=1.0.2
Requires-Dist: lifelines>=0.27.8
Requires-Dist: scikit-survival>=0.24
Requires-Dist: openpyxl
Dynamic: author
Dynamic: author-email
Dynamic: description
Dynamic: keywords
Dynamic: license
Dynamic: license-file
Dynamic: requires-dist
Dynamic: requires-python
